sortingshop/__init__.py
sortingshop/config.py
sortingshop/exiftool.py
sortingshop/singleton.py
sortingshop/sortingshop.py
sortingshop/log/__init__.py
sortingshop/log/log.py
sortingshop/media/__init__.py
sortingshop/media/mediafile.py
sortingshop/media/medialist.py
sortingshop/media/metadatasource.py
sortingshop/media/sidecar.py
sortingshop/media/taglist.py
sortingshop/media/tagsets.py
sortingshop/settings/config.ini
sortingshop/ui/__init__.py
sortingshop/ui/ui.py
sortingshop/ui/wxpython.py
sortingshop/ui/resources/default.jpeg
sortingshop/ui/resources/default.png
sortingshop/ui/resources/sosho.ico
sortingshop/ui/resources/sosho.svg
sortingshop-1.1.1.dist-info/LICENSE
sortingshop-1.1.1.dist-info/METADATA
sortingshop-1.1.1.dist-info/WHEEL
sortingshop-1.1.1.dist-info/entry_points.txt
sortingshop-1.1.1.dist-info/top_level.txt
sortingshop-1.1.1.dist-info/RECORD
