Metadata-Version: 2.1
Name: sortingshop
Version: 1.1.1
Author-email: Eike Kühn <eike.kuehn@pixelwoelkchen.de>
Maintainer-email: Eike Kühn <eike.kuehn@pixelwoelkchen.de>
Project-URL: homepage, https://github.com/randomchars42/sortingshop
Project-URL: documentation, https://github.com/randomchars42/sortingshop
Project-URL: source, https://github.com/randomchars42/sortingshop
Project-URL: tracker, https://github.com/randomchars42/sortingshop/issues
Classifier: License :: OSI Approved :: The Unlicense (Unlicense)
Classifier: Programming Language :: Python :: 3
Classifier: Programming Language :: Python :: 3.6
Classifier: Programming Language :: Python :: 3.7
Classifier: Programming Language :: Python :: 3.8
Classifier: Programming Language :: Python :: 3.9
Classifier: Programming Language :: Python :: 3.10
Classifier: Programming Language :: Python :: 3 :: Only
Classifier: Development Status :: 5 - Production/Stable
Classifier: Programming Language :: Python
Requires-Python: >=3.6
License-File: LICENSE
Requires-Dist: attrdict3
Requires-Dist: wxPython (~=4.2.0)
